alert2issue.py
alert2issue-0.2.0.dist-info/licenses/LICENSE
alert2issue-0.2.0.dist-info/METADATA
alert2issue-0.2.0.dist-info/WHEEL
alert2issue-0.2.0.dist-info/entry_points.txt
alert2issue-0.2.0.dist-info/top_level.txt
alert2issue-0.2.0.dist-info/RECORD
