Metadata-Version: 2.4
Name: alert2issue
Version: 0.2.0
Summary: Automatically create GitHub issues from open Dependabot alerts
Author: Anne Jan Brouwer
License-Expression: MIT
Project-URL: Homepage, https://github.com/annejan/github-create-dependabot-alert-issues
Keywords: Dependabot,GitHub,alert,issue,no-patch
License-File: LICENSE
Requires-Dist: requests
Dynamic: license-file
